LICENSE
MANIFEST.in
README.rst
setup.cfg
setup.py
bin/ptree
cyw_bogus_0.1.95.egg-info/PKG-INFO
cyw_bogus_0.1.95.egg-info/SOURCES.txt
cyw_bogus_0.1.95.egg-info/dependency_links.txt
cyw_bogus_0.1.95.egg-info/requires.txt
cyw_bogus_0.1.95.egg-info/top_level.txt
django_ptree/__init__.py
django_ptree/settings.py
django_ptree/urls.py
django_ptree/wsgi.py
docs/Makefile
docs/conf.py
docs/deploy.rst
docs/index.rst
docs/make.bat
docs/prerequisites.rst
docs/setup.rst
docs/_build/doctrees/administering.doctree
docs/_build/doctrees/app.doctree
docs/_build/doctrees/deploying.doctree
docs/_build/doctrees/environment.pickle
docs/_build/doctrees/index.doctree
docs/_build/doctrees/installation.doctree
docs/_build/doctrees/intro.doctree
docs/_build/doctrees/prerequisites.doctree
docs/_build/doctrees/project.doctree
docs/_build/html/app/auxiliary-models.html
docs/app/admin.rst
docs/app/auxiliary-models.rst
docs/app/forms.rst
docs/app/index.rst
docs/app/management.rst
docs/app/model-hierarchy.png
docs/app/models.rst
docs/app/templates.rst
docs/app/views.rst
ptree/__init__.py
ptree/admin.py
ptree/app_template.zip
ptree/common.py
ptree/constants.py
ptree/fields.py
ptree/forms.py
ptree/project_template.zip
ptree/settings.py
ptree/urls.py
ptree/locale/de/LC_MESSAGES/django.mo
ptree/locale/de/LC_MESSAGES/django.po
ptree/management/__init__.py
ptree/management/commands/__init__.py
ptree/management/commands/create_experiments.py
ptree/management/commands/mturk_pay.py
ptree/models/__init__.py
ptree/models/common.py
ptree/models/experiments.py
ptree/models/matches.py
ptree/models/participants.py
ptree/models/treatments.py
ptree/questionnaires/__init__.py
ptree/questionnaires/life_orientation_test/__init__.py
ptree/questionnaires/life_orientation_test/admin.py
ptree/questionnaires/life_orientation_test/forms.py
ptree/questionnaires/life_orientation_test/models.py
ptree/questionnaires/life_orientation_test/views.py
ptree/questionnaires/new_general_self_efficacy_scale/__init__.py
ptree/questionnaires/new_general_self_efficacy_scale/admin.py
ptree/questionnaires/new_general_self_efficacy_scale/forms.py
ptree/questionnaires/new_general_self_efficacy_scale/models.py
