Metadata-Version: 1.1
Name: cyw-bogus-0.1.95
Version: 0.1.95
Summary: For mighty refuge.
Home-page: http://ptree.org/
Author: Chris Wickens
Author-email: c.wickens+ptree@googlemail.com
License: MIT License
Platform: UNKNOWN
Classifier: Environment :: Web Environment
Classifier: Framework :: Django
Classifier: Intended Audience :: Developers
Classifier: License :: OSI Approved :: MIT License
Classifier: Operating System :: OS Independent
Classifier: Programming Language :: Python
Classifier: Programming Language :: Python :: 2
Classifier: Programming Language :: Python :: 2.7
Classifier: Topic :: Internet :: WWW/HTTP
Classifier: Topic :: Internet :: WWW/HTTP :: Dynamic Content
